examples/__init__.py
examples/generate_text.py
examples/train_lora/__init__.py
examples/train_lora/gutenberg.py
examples/train_lora/train.py
openelm_pytorch/__init__.py
openelm_pytorch/config.py
openelm_pytorch/openelm.py
openelm_pytorch/tokenizer.py
openelm_pytorch/utils.py
openelm_pytorch-0.1.0.dist-info/LICENSE
openelm_pytorch-0.1.0.dist-info/METADATA
openelm_pytorch-0.1.0.dist-info/WHEEL
openelm_pytorch-0.1.0.dist-info/top_level.txt
openelm_pytorch-0.1.0.dist-info/RECORD
