Metadata-Version: 2.1
Name: openelm-pytorch
Version: 0.1.0
Summary: openelm-pytorch
Author-email: Frank Odom <frank.odom.iii@gmail.com>
License: MIT
Classifier: Programming Language :: Python :: 3
Requires-Python: >=3.9
License-File: LICENSE
Requires-Dist: safetensors <1,>=0.4.0
Requires-Dist: torch <3.0,>=2.0
Provides-Extra: mlx
Requires-Dist: mlx <1,>=0.10.0 ; extra == 'mlx'
Provides-Extra: test
Requires-Dist: black ==24.4.2 ; extra == 'test'
Requires-Dist: mlx ==0.10.0 ; extra == 'test'
Requires-Dist: mypy ==1.10.0 ; extra == 'test'
Requires-Dist: numpy ==1.26.4 ; extra == 'test'
Requires-Dist: pre-commit ==3.7.0 ; extra == 'test'
Requires-Dist: pytest ==8.1.2 ; extra == 'test'
Requires-Dist: pytest-cov ==5.0.0 ; extra == 'test'
Requires-Dist: ruff ==0.4.2 ; extra == 'test'
Requires-Dist: sentencepiece ==0.2.0 ; extra == 'test'
Provides-Extra: train
Requires-Dist: lora-pytorch ~=0.2.0 ; extra == 'train'
Requires-Dist: lightning ~=2.2.0 ; extra == 'train'
Requires-Dist: tensorboard ~=2.14.0 ; extra == 'train'
Requires-Dist: tqdm ; extra == 'train'
